berny/Math.py
berny/__init__.py
berny/berny.py
berny/cli.py
berny/coords.py
berny/geomlib.py
berny/optimize.py
berny/solvers.py
berny/species-data.csv
berny/species_data.py
pyberny-0.6.2.dist-info/entry_points.txt
pyberny-0.6.2.dist-info/LICENSE
pyberny-0.6.2.dist-info/WHEEL
pyberny-0.6.2.dist-info/METADATA
pyberny-0.6.2.dist-info/RECORD
