Metadata-Version: 2.1
Name: pyberny
Version: 0.6.2
Summary: Molecular/crystal structure optimizer
Home-page: https://github.com/jhrmnn/pyberny
License: MPL-2.0
Author: Jan Hermann
Author-email: dev@jan.hermann.name
Requires-Python: >=3.5,<4.0
Classifier: Environment :: Console
Classifier: Intended Audience :: Science/Research
Classifier: License :: OSI Approved
Classifier: Operating System :: POSIX
Classifier: Programming Language :: Python :: 3
Classifier: Programming Language :: Python :: 3.5
Classifier: Programming Language :: Python :: 3.6
Classifier: Programming Language :: Python :: 3.7
Classifier: Programming Language :: Python :: 3.8
Classifier: Topic :: Scientific/Engineering :: Chemistry
Classifier: Topic :: Scientific/Engineering :: Physics
Provides-Extra: doc
Provides-Extra: test
Requires-Dist: coverage (>=4.5,<5.0); extra == "test"
Requires-Dist: importlib-metadata (>=1.5.0,<2.0.0); extra == "doc"
Requires-Dist: numpy (>=1.15,<2.0)
Requires-Dist: pytest (>=3.6,<4.0); extra == "test"
Requires-Dist: sphinx (>=2.2,<3.0); extra == "doc"
Requires-Dist: sphinxcontrib-katex (>=0.5.1,<0.6.0); extra == "doc"
Project-URL: Documentation, https://jhrmnn.github.io/pyberny
Project-URL: Repository, https://github.com/jhrmnn/pyberny
